DataAdaptor/__init__.py
DataAdaptor/config.py
DataAdaptor/input.py
DataAdaptor/test.py
data_adaptor-0.1.5.dist-info/LICENSE
data_adaptor-0.1.5.dist-info/METADATA
data_adaptor-0.1.5.dist-info/WHEEL
data_adaptor-0.1.5.dist-info/top_level.txt
data_adaptor-0.1.5.dist-info/RECORD
