Metadata-Version: 2.1
Name: data-adaptor
Version: 0.1.5
Summary: Input Adaptor to verify file extension
Author: Crossml
Author-email: amar@crossml.com
License: MIT
Keywords: Input-adaptor,Adaptor,DataAdaptor
Platform: UNKNOWN
Requires-Python: >=3
License-File: LICENSE
Requires-Dist: boto3
Requires-Dist: requests
